MANIFEST.in
README.txt
setup.cfg
setup.py
adi/__init__.py
adi.init.egg-info/PKG-INFO
adi.init.egg-info/SOURCES.txt
adi.init.egg-info/dependency_links.txt
adi.init.egg-info/entry_points.txt
adi.init.egg-info/namespace_packages.txt
adi.init.egg-info/not-zip-safe
adi.init.egg-info/paster_plugins.txt
adi.init.egg-info/requires.txt
adi.init.egg-info/top_level.txt
adi/init/__init__.py
adi/init/configure.zcml
adi/init/setuphandlers.py
adi/init/tests.py
adi/init/profiles/default/adi.init.marker.txt
adi/init/profiles/default/metadata.xml
adi/init/profiles/default/portlets.xml
docs/HISTORY.txt
docs/INSTALL.txt
docs/LICENSE.GPL
docs/LICENSE.txt