Metadata-Version: 1.0
Name: adi.init
Version: 0.4
Summary: Deletes Plone's default contents
Home-page: http://svn.plone.org/svn/collective/
Author: Ida Ebkes
Author-email: contact@ida-ebkes.eu
License: GPL
Platform: UNKNOWN
Classifier: Framework :: Plone
Classifier: Programming Language :: Python
